torch_ppr/__init__.py
torch_ppr/api.py
torch_ppr/py.typed
torch_ppr/utils.py
torch_ppr/version.py
torch_ppr-0.0.8.dist-info/LICENSE
torch_ppr-0.0.8.dist-info/METADATA
torch_ppr-0.0.8.dist-info/WHEEL
torch_ppr-0.0.8.dist-info/top_level.txt
torch_ppr-0.0.8.dist-info/RECORD
