Metadata-Version: 2.1
Name: torch-ppr
Version: 0.0.8
Summary: (Personalized) Page-Rank computation using PyTorch
Home-page: https://github.com/mberr/torch-ppr
Download-URL: https://github.com/mberr/torch-ppr/releases
Author: Max Berrendorf
Author-email: max.berrendorf@gmail.com
Maintainer: Max Berrendorf
Maintainer-email: max.berrendorf@gmail.com
License: MIT
Project-URL: Bug Tracker, https://github.com/mberr/torch-ppr/issues
Project-URL: Source Code, https://github.com/mberr/torch-ppr
Keywords: snekpack,cookiecutter
Classifier: Development Status :: 1 - Planning
Classifier: Environment :: Console
Classifier: Intended Audience :: Developers
Classifier: License :: OSI Approved :: MIT License
Classifier: Operating System :: OS Independent
Classifier: Framework :: Pytest
Classifier: Framework :: tox
Classifier: Framework :: Sphinx
Classifier: Programming Language :: Python
Classifier: Programming Language :: Python :: 3.8
Classifier: Programming Language :: Python :: 3.9
Classifier: Programming Language :: Python :: 3.10
Classifier: Programming Language :: Python :: 3 :: Only
Requires-Python: >=3.8
License-File: LICENSE
Requires-Dist: more-itertools
Requires-Dist: tqdm
Requires-Dist: torch (>=1.11)
Requires-Dist: torch-max-mem
Provides-Extra: docs
Requires-Dist: sphinx ; extra == 'docs'
Requires-Dist: sphinx-rtd-theme ; extra == 'docs'
Requires-Dist: sphinx-autodoc-typehints ; extra == 'docs'
Requires-Dist: sphinx-automodapi ; extra == 'docs'
Provides-Extra: tests
Requires-Dist: pytest ; extra == 'tests'
Requires-Dist: coverage ; extra == 'tests'
